sikufenci/__init__.py
sikufenci/bert.py
sikufenci/run_ner.py
sikufenci/settings.py
sikufenci/wordseg.py
sikufenci/wordsegall_txt.py
sikufenci/wordsegtry.py
sikufenci/data/__init__.py
sikufenci/data/test.txt
sikufenci/final_result/__init__.py
sikufenci/final_result/test_result.txt
sikufenci/outputdata/__init__.py
sikufenci/outputdata/labeled_results.txt
sikufenci/pretrain_models/sikuroberta_vocabtxt/bert_config.json
sikufenci/pretrain_models/sikuroberta_vocabtxt/vocab.txt
sikufenci/train_fenci_sikuroberta_vocabtxt/__init__.py
sikufenci/train_fenci_sikuroberta_vocabtxt/bert_config.json
sikufenci/train_fenci_sikuroberta_vocabtxt/labeled_results.txt
sikufenci/wordseg_data/__init__.py
sikufenci/wordseg_data/dev.txt
sikufenci/wordseg_data/test.txt
sikufenci/wordseg_data/train.txt
sikufenci/wordseg_data/valid.txt
sikufenci-0.0.29.dist-info/METADATA
sikufenci-0.0.29.dist-info/WHEEL
sikufenci-0.0.29.dist-info/top_level.txt
sikufenci-0.0.29.dist-info/RECORD
