Metadata-Version: 2.1
Name: sikufenci
Version: 0.0.29
Summary: NLP tool for Ancient Chinese word segmentation.
Home-page: https://github.com/SIKU-BERT/sikufenci
Author: Liu Chang
Author-email: 649164915@qq.com
License: MIT
Keywords: classical-chinese,wordseg,nlp
Platform: UNKNOWN
Classifier: Programming Language :: Python
Classifier: Programming Language :: Python :: 2
Classifier: Programming Language :: Python :: 2.6
Classifier: Programming Language :: Python :: 2.7
Classifier: Programming Language :: Python :: 3
Classifier: Programming Language :: Python :: 3.3
Classifier: Programming Language :: Python :: 3.4
Classifier: Programming Language :: Python :: 3.5
Classifier: Programming Language :: Python :: 3.6
Classifier: Topic :: Utilities
Classifier: Topic :: Text Processing
Requires-Python: >=2.6, >=3
Requires-Dist: torch (>=1.1.0)
Requires-Dist: boto3
Requires-Dist: pytorch-pretrained-bert (==0.6.1)
Requires-Dist: requests
Requires-Dist: tqdm
Requires-Dist: seqeval (>=0.0.5)
Requires-Dist: numpy
Requires-Dist: argparse ; python_version<"2.7"
Requires-Dist: enum34 ; python_version<"3.4"
Requires-Dist: typing ; python_version<"3.5"
